kvrocks_dao/__init__.py
kvrocks_dao/common/__init__.py
kvrocks_dao/common/dao.py
kvrocks_dao/common/entity.py
kvrocks_dao-0.0.7.dist-info/METADATA
kvrocks_dao-0.0.7.dist-info/WHEEL
kvrocks_dao-0.0.7.dist-info/top_level.txt
kvrocks_dao-0.0.7.dist-info/RECORD
