Metadata-Version: 2.1
Name: kvrocks_dao
Version: 0.0.7
Summary: Testing
Author-email: Example Author <author@example.com>
Classifier: Programming Language :: Python :: 3
Classifier: License :: OSI Approved :: MIT License
Classifier: Operating System :: OS Independent
Requires-Python: >=3.8
